pddlpy/__init__.py
pddlpy/pddl.py
pddlpy/pddlLexer.py
pddlpy/pddlListener.py
pddlpy/pddlParser.py
pddlpy/test.py
pddlpy-0.4.4.data/data/examples/domain-01.pddl
pddlpy-0.4.4.data/data/examples/domain-02.pddl
pddlpy-0.4.4.data/data/examples/domain-03.pddl
pddlpy-0.4.4.data/data/examples/domain-04.pddl
pddlpy-0.4.4.data/data/examples/domain-05.pddl
pddlpy-0.4.4.data/data/examples/domain-06.pddl
pddlpy-0.4.4.data/data/examples/problem-01.pddl
pddlpy-0.4.4.data/data/examples/problem-02.pddl
pddlpy-0.4.4.data/data/examples/problem-03.pddl
pddlpy-0.4.4.data/data/examples/problem-04.pddl
pddlpy-0.4.4.data/data/examples/problem-05.pddl
pddlpy-0.4.4.data/data/examples/problem-06.pddl
pddlpy-0.4.4.dist-info/LICENSE.txt
pddlpy-0.4.4.dist-info/METADATA
pddlpy-0.4.4.dist-info/WHEEL
pddlpy-0.4.4.dist-info/top_level.txt
pddlpy-0.4.4.dist-info/RECORD
