Metadata-Version: 2.1
Name: pddlpy
Version: 0.4.4
Summary: Python PDDL parser
Home-page: https://github.com/hfoffani/pddl-lib
Author: Hernan Foffani
Author-email: hfoffani@gmail.com
License: MIT
Keywords: pddl planning parser
Classifier: Development Status :: 3 - Alpha
Classifier: Intended Audience :: Developers
Classifier: Topic :: Software Development :: Build Tools
Classifier: License :: OSI Approved :: MIT License
Classifier: Programming Language :: Python :: 3
Classifier: Programming Language :: Python :: 3.11
License-File: LICENSE.txt
Requires-Dist: antlr4-python3-runtime (==4.13.1)
